s3simplemanager/__init__.py
s3simplemanager/s3manager.py
s3simplemanager-1.2.dist-info/METADATA
s3simplemanager-1.2.dist-info/WHEEL
s3simplemanager-1.2.dist-info/licenses/LICENSE
s3simplemanager-1.2.dist-info/RECORD
