Metadata-Version: 2.4
Name: s3simplemanager
Version: 1.2
Summary: This package will allow an easier interaction with s3 buckets.
Project-URL: Homepage, https://bitbucket.org/JoaoChamine/s3simplemanager/
Project-URL: Issues, https://bitbucket.org/JoaoChamine/s3simplemanager/issues
Author-email: Joao Chamine <jchamine@outlook.pt>
License-File: LICENSE
Classifier: License :: OSI Approved :: MIT License
Classifier: Operating System :: OS Independent
Classifier: Programming Language :: Python :: 3
Requires-Python: >=3.12
Requires-Dist: boto3
